sensorsanalytics/__init__.py
sensorsanalytics/sdk.py
sensorsanalytics/test_sdk.py
SensorsAnalyticsSDK-1.11.0.dist-info/LICENSE
SensorsAnalyticsSDK-1.11.0.dist-info/METADATA
SensorsAnalyticsSDK-1.11.0.dist-info/WHEEL
SensorsAnalyticsSDK-1.11.0.dist-info/top_level.txt
SensorsAnalyticsSDK-1.11.0.dist-info/RECORD
