Metadata-Version: 2.1
Name: SensorsAnalyticsSDK
Version: 1.11.0
Summary: This is the official Python SDK for Sensors Analytics.
Home-page: https://github.com/sensorsdata/sa-sdk-python
Author: Jianzhong YUE
Author-email: yuejianzhong@sensorsdata.cn
License: UNKNOWN
Platform: UNKNOWN
